{
  "40000": "https://support.ably.io/solution/articles/3000082819",
  "40001": "https://support.ably.io/solution/articles/3000085256",
  "40005": "https://support.ably.io/solution/articles/3000083030",
  "40009": "https://support.ably.io/solution/articles/3000083028",
  "40010": "https://support.ably.io/solution/articles/3000046824",
  "40012": "https://support.ably.io/solution/articles/3000089431",
  "40101": "https://support.ably.io/solution/articles/3000067415",
  "40103": "https://support.ably.io/solution/articles/3000065731",
  "40104": "https://support.ably.io/solution/articles/3000068941",
  "40105": "https://support.ably.io/solution/articles/3000068938",
  "40112": "https://support.ably.io/solution/articles/3000083036",
  "40115": "https://support.ably.io/solution/articles/3000082891",
  "40131": "https://support.ably.io/solution/articles/3000082888",
  "40142": "https://support.ably.io/solution/articles/3000081686",
  "40143": "https://support.ably.io/solution/articles/3000081687",
  "40144": "https://support.ably.io/solution/articles/3000080687",
  "40160": "https://support.ably.io/solution/articles/3000081689",
  "40161": "https://support.ably.io/solution/articles/3000090590",
  "40171": "https://support.ably.io/solution/articles/3000089429",
  "40300": "https://support.ably.io/solution/articles/3000081685",
  "40330": "https://support.ably.io/solution/articles/3000081967",
  "40331": "https://support.ably.io/solution/articles/3000081969",
  "40332": "https://support.ably.io/solution/articles/3000081968",
  "40400": "https://support.ably.io/solution/articles/3000089430",
  "42910": "https://support.ably.io/solution/articles/3000082363",
  "42911": "https://support.ably.io/solution/articles/3000081684",
  "50000": "https://support.ably.io/solution/articles/3000083448",
  "50003": "https://support.ably.io/solution/articles/3000083450",
  "80000": "https://support.ably.io/solution/articles/3000092531",
  "80008": "https://support.ably.io/solution/articles/3000081690",
  "80016": "https://support.ably.io/solution/articles/3000089432",
  "80017": "https://support.ably.io/solution/articles/3000092530",
  "90001": "https://support.ably.io/solution/articles/3000089433",
  "90010": "https://support.ably.io/solution/articles/3000081688"
}
